{
  "gameNumber": 838,
  "date": "2027-04-21",
  "questions": [
    {
      "quote": "No-no-no, Kramer. Kramer! Kramer! You *cannot* abandon people in the middle of an airport pickup! It's a binding social contract. We... we must go forward... not back.",
      "characters": [
        "Frank",
        "George",
        "Dan",
        "Jerry"
      ],
      "correctAnswer": "George"
    },
    {
      "quote": "Let go, Farfel! Let go, gimme that! Gimme the sneaker you stupid idiot! Shut up!  So what would you do?",
      "characters": [
        "Valerie",
        "Kramer",
        "Jerry",
        "George"
      ],
      "correctAnswer": "Jerry"
    },
    {
      "quote": "Ha ha ha ha!!! That's killer! Killer! I love that! Ha ha ha!!! You gotta use that, that's a definite!! Ha ha ha!!!",
      "characters": [
        "Jerry",
        "Mike",
        "Kramer",
        "Bania"
      ],
      "correctAnswer": "Mike"
    },
    {
      "quote": "Well as a woman, it makes no sense. But, I mean, let's say I was you. And I decided I was gonna change my name for no real reasons whatsoever-- Deon Rifkin. Wow! That is so cool.",
      "characters": [
        "Jake",
        "Kramer",
        "Elaine",
        "George"
      ],
      "correctAnswer": "Elaine"
    },
    {
      "quote": "Hey, hey, hey! All right! Yeah, uh, yeah.. well.. Uh, the pants. they, uh, they fit, uh, well - and so I, uh, decided I wasn't gonna return them!  Wooh-hoo-hoo-hoo!",
      "characters": [
        "George",
        "Elaine",
        "Kramer",
        "Tom"
      ],
      "correctAnswer": "Kramer"
    },
    {
      "quote": "Well, after we met, you were all so nice. I just couldn't go through with it. But between you and me, you would have paid through the nose.",
      "characters": [
        "Jerry",
        "Marcy",
        "Peterman",
        "Cheryl"
      ],
      "correctAnswer": "Cheryl"
    },
    {
      "quote": "She hasn't seen the article! When she sees it, she's gonna think-- *I'm out baby*!! I'm out!!!!!",
      "characters": [
        "George",
        "Kramer",
        "Jerry",
        "Elaine"
      ],
      "correctAnswer": "George"
    },
    {
      "quote": "Kramer, what are you talking about...Janet doesn't look anything like Jerry",
      "characters": [
        "Elaine",
        "Kramer",
        "Jerry",
        "George"
      ],
      "correctAnswer": "George"
    },
    {
      "quote": "Look Mister Costanza, it's too late now anyway. I already made a deal with another writing team.",
      "characters": [
        "Jerry",
        "Elaine",
        "George",
        "Russell"
      ],
      "correctAnswer": "Russell"
    },
    {
      "quote": "Look at this poor guy. His family is probably in Pakistan -- they're waiting him to send back money. This is horrible.",
      "characters": [
        "Jerry",
        "Elaine",
        "Keith",
        "George"
      ],
      "correctAnswer": "Jerry"
    }
  ]
}