{
  "gameNumber": 831,
  "date": "2027-04-13",
  "questions": [
    {
      "quote": "Look, forget about the receipt, all right? Even if I had the receipt- look at it! It's a hand puppet. What am I gonna do with this?!",
      "characters": [
        "Jerry",
        "Elaine",
        "George",
        "Marlene"
      ],
      "correctAnswer": "Jerry"
    },
    {
      "quote": "Well, we could fly some fabric in from our silk factories, for about a thousand dollars a bolt.",
      "characters": [
        "Elaine",
        "Morty",
        "Kramer",
        "George"
      ],
      "correctAnswer": "Elaine"
    },
    {
      "quote": "Listen, do you think I take everything everybody offers me? You offered me sponge cake yesterday. Did I take it?",
      "characters": [
        "Lloyd",
        "Jack",
        "George",
        "Elaine"
      ],
      "correctAnswer": "Jack"
    },
    {
      "quote": "Well, uh, I'd watch the third base coach if I were you 'cause I don't think he's waving you in. You know I hate to say this but I think we're really hitting it off. Get it? Get it?",
      "characters": [
        "Susan",
        "George",
        "Kramer",
        "Elaine"
      ],
      "correctAnswer": "Elaine"
    },
    {
      "quote": "Ever since I found out that you let that message on Jerry's tape recorder I...",
      "characters": [
        "Jerry",
        "Kramer",
        "George",
        "Newman"
      ],
      "correctAnswer": "George"
    },
    {
      "quote": "I was very upset that day because I could never become a banker.",
      "characters": [
        "Jerry",
        "Maestro",
        "Kramer",
        "Dana"
      ],
      "correctAnswer": "Kramer"
    },
    {
      "quote": "Yeah.  And by the way, can you get this thing outta my house?",
      "characters": [
        "Jerry",
        "Elaine",
        "Sophie",
        "George"
      ],
      "correctAnswer": "Jerry"
    },
    {
      "quote": "Well if that air is comming out of this face then it is my air and my idea.",
      "characters": [
        "Elaine",
        "Jerry",
        "Tor",
        "Kramer"
      ],
      "correctAnswer": "Elaine"
    },
    {
      "quote": "I wish he was not in a coma. I wish he was dead. I wish I could pull the plug out from him.",
      "characters": [
        "Gina",
        "Elaine",
        "Jerry",
        "Puddy"
      ],
      "correctAnswer": "Gina"
    },
    {
      "quote": "Say you go to the bathroom at two o'clock in the morning, what's the outfit?  I mean, you dressing up or is it come as you are?",
      "characters": [
        "Jerry",
        "George",
        "Kramer",
        "Alton"
      ],
      "correctAnswer": "George"
    }
  ]
}