{
  "gameNumber": 1636,
  "date": "2029-07-16",
  "questions": [
    {
      "quote": "So umm, you feel like taking a test? There's only one question.",
      "characters": [
        "Joey",
        "Monica",
        "Director",
        "Alice Knight"
      ],
      "correctAnswer": "Alice Knight"
    },
    {
      "quote": "Well I'm gonna be on it this year. I'm gonna be one of the party people.",
      "characters": [
        "Janine Lecroix",
        "Joey",
        "Chandler",
        "Janice"
      ],
      "correctAnswer": "Janine Lecroix"
    },
    {
      "quote": "So you have to tell Monica you don't want to have a baby right now?",
      "characters": [
        "Rachel",
        "Chandler",
        "Joey",
        "Ross"
      ],
      "correctAnswer": "Ross"
    },
    {
      "quote": "Hey, have you seen Frank Jr., 'cause he's meeting me here with the triplets.",
      "characters": [
        "Phoebe",
        "Rachel",
        "Chandler",
        "Paul Stevens"
      ],
      "correctAnswer": "Phoebe"
    },
    {
      "quote": "Barbara! Hi, how are you? Uh-huh. No, I understand. Yeah. Oh, oh, come on, no, I'm fine. Don't be silly. Yeah... oh, but you know, if-if anything else opens up, pleaHello? Hello?",
      "characters": [
        "Ross",
        "Chandler",
        "Joey",
        "Rachel"
      ],
      "correctAnswer": "Rachel"
    },
    {
      "quote": "Sure, yeah. I mean, it's Joey. I don't want him to get hurt. Well, I must say, I am on fire! First Chandler, now Joey!",
      "characters": [
        "Phoebe",
        "Joey",
        "Monica",
        "Ross"
      ],
      "correctAnswer": "Phoebe"
    },
    {
      "quote": "Phoebe, you get the bear, uhm, Joey, you get the robot, and Chandler and I get the dog. Ok, and the race is going to go from here to here. Now the one who comes in last, stays!",
      "characters": [
        "Joey",
        "Monica",
        "Ross",
        "Phoebe"
      ],
      "correctAnswer": "Monica"
    },
    {
      "quote": "No I'm not sure that it's the best way to hear everything. Someone get me a glass!",
      "characters": [
        "Rachel",
        "Chandler",
        "Monica",
        "The Salesman"
      ],
      "correctAnswer": "Monica"
    },
    {
      "quote": "No way! You had your party, now I have mine! Is everything alright?",
      "characters": [
        "Ross",
        "Joey",
        "Monica",
        "Chandler"
      ],
      "correctAnswer": "Monica"
    },
    {
      "quote": "Okay. Then, take the tiara back and let me hold the musket again. Something's missing. It's not... Okay oh, let me see the ring my friend picked out.",
      "characters": [
        "Gunther",
        "Trudie Styler",
        "Joey",
        "Phoebe"
      ],
      "correctAnswer": "Phoebe"
    }
  ]
}