{
  "gameNumber": 697,
  "date": "2026-11-30",
  "questions": [
    {
      "quote": "That is it! Mary Hart's voice, don't you see? There's something about Mary Hart's voice that's giving you seizures. Just like, just like, just like that woman in Albany!",
      "characters": [
        "Elaine",
        "Kramer",
        "Melissa",
        "George"
      ],
      "correctAnswer": "Elaine"
    },
    {
      "quote": "Yeah. I love Hampton tomatoes. You know, you can eat 'em like apples. You know it's funny, the tomato never really took on as a hand fruit.",
      "characters": [
        "George",
        "Jerry",
        "Kramer",
        "Elaine"
      ],
      "correctAnswer": "George"
    },
    {
      "quote": "Listen, listen I'm gonna go call work to see if I can get my deadline extended. I can't...come up with anything for this thing.",
      "characters": [
        "Hanke",
        "Elaine",
        "Joe",
        "Kramer"
      ],
      "correctAnswer": "Elaine"
    },
    {
      "quote": "I don't have a spare set. All my keys say 'do not duplicate'.",
      "characters": [
        "Morty",
        "Elaine",
        "Jerry",
        "George"
      ],
      "correctAnswer": "George"
    },
    {
      "quote": "Elaine it's her cat. Her cat had the fungus. So I need the tube back.",
      "characters": [
        "Jerry",
        "Elaine",
        "Receptionist",
        "Lloyd"
      ],
      "correctAnswer": "Jerry"
    },
    {
      "quote": "No, I have thought about you many times. Have you thought about me?",
      "characters": [
        "George",
        "Elaine",
        "Gina",
        "Kramer"
      ],
      "correctAnswer": "Gina"
    },
    {
      "quote": "I've heard of Ohio, Katie. But Tuesday's no good. I'm doin' career day at my old junior high.",
      "characters": [
        "Donald",
        "Jerry",
        "Elaine",
        "George"
      ],
      "correctAnswer": "Jerry"
    },
    {
      "quote": "You know, the thing is, I kinda promised the widow Mantle that I would name my baby Seven.",
      "characters": [
        "Elaine",
        "Jerry",
        "George",
        "Puddy"
      ],
      "correctAnswer": "George"
    },
    {
      "quote": "Believe me, Jerry, somewhere in this hospital the anguished \"oink\" of pig-man cries out for help.",
      "characters": [
        "Kramer",
        "Jerry",
        "Elaine",
        "George"
      ],
      "correctAnswer": "Kramer"
    },
    {
      "quote": "Lunch is fine at the beginning then you move on to dinner. you don't move back to lunch. It's like being demoted. I'll never do another crossword puzzle with her again. I know it.",
      "characters": [
        "Jerry",
        "George",
        "Ruby",
        "Kramer"
      ],
      "correctAnswer": "George"
    }
  ]
}